{
	"backtrace" : 2,
	"backtraceGraph" : 
	{
		"commands" : 
		[
			"add_custom_target",
			"ExternalProject_Add"
		],
		"files" : 
		[
			"C:/Program Files/Microsoft Visual Studio/2022/Community/Common7/IDE/CommonExtensions/Microsoft/CMake/CMake/share/cmake-3.21/Modules/ExternalProject.cmake",
			"CMakeLists.txt"
		],
		"nodes" : 
		[
			{
				"file" : 1
			},
			{
				"command" : 1,
				"file" : 1,
				"line" : 5,
				"parent" : 0
			},
			{
				"command" : 0,
				"file" : 0,
				"line" : 3514,
				"parent" : 1
			}
		]
	},
	"folder" : 
	{
		"name" : "ExternalProjectTargets/pahomqttc"
	},
	"id" : "pahomqttc::@6890427a1f51a3e7e1df",
	"name" : "pahomqttc",
	"paths" : 
	{
		"build" : ".",
		"source" : "."
	},
	"sourceGroups" : 
	[
		{
			"name" : "",
			"sourceIndexes" : 
			[
				0
			]
		},
		{
			"name" : "CMake Rules",
			"sourceIndexes" : 
			[
				1,
				2,
				3,
				4,
				5,
				6,
				7,
				8,
				9
			]
		}
	],
	"sources" : 
	[
		{
			"backtrace" : 2,
			"isGenerated" : true,
			"path" : "out/build/x64-Debug/CMakeFiles/pahomqttc",
			"sourceGroupIndex" : 0
		},
		{
			"backtrace" : 0,
			"isGenerated" : true,
			"path" : "out/build/x64-Debug/CMakeFiles/pahomqttc.rule",
			"sourceGroupIndex" : 1
		},
		{
			"backtrace" : 0,
			"isGenerated" : true,
			"path" : "out/build/x64-Debug/CMakeFiles/pahomqttc-complete.rule",
			"sourceGroupIndex" : 1
		},
		{
			"backtrace" : 0,
			"isGenerated" : true,
			"path" : "out/build/x64-Debug/pahomqttc-prefix/src/pahomqttc-stamp/pahomqttc-build.rule",
			"sourceGroupIndex" : 1
		},
		{
			"backtrace" : 0,
			"isGenerated" : true,
			"path" : "out/build/x64-Debug/pahomqttc-prefix/src/pahomqttc-stamp/pahomqttc-configure.rule",
			"sourceGroupIndex" : 1
		},
		{
			"backtrace" : 0,
			"isGenerated" : true,
			"path" : "out/build/x64-Debug/pahomqttc-prefix/src/pahomqttc-stamp/pahomqttc-download.rule",
			"sourceGroupIndex" : 1
		},
		{
			"backtrace" : 0,
			"isGenerated" : true,
			"path" : "out/build/x64-Debug/pahomqttc-prefix/src/pahomqttc-stamp/pahomqttc-install.rule",
			"sourceGroupIndex" : 1
		},
		{
			"backtrace" : 0,
			"isGenerated" : true,
			"path" : "out/build/x64-Debug/pahomqttc-prefix/src/pahomqttc-stamp/pahomqttc-mkdir.rule",
			"sourceGroupIndex" : 1
		},
		{
			"backtrace" : 0,
			"isGenerated" : true,
			"path" : "out/build/x64-Debug/pahomqttc-prefix/src/pahomqttc-stamp/pahomqttc-patch.rule",
			"sourceGroupIndex" : 1
		},
		{
			"backtrace" : 0,
			"isGenerated" : true,
			"path" : "out/build/x64-Debug/pahomqttc-prefix/src/pahomqttc-stamp/pahomqttc-update.rule",
			"sourceGroupIndex" : 1
		}
	],
	"type" : "UTILITY"
}
